scholarqa/__init__.py
scholarqa/app.py
scholarqa/glog.py
scholarqa/models.py
scholarqa/scholar_qa.py
scholarqa/trial.py
scholarqa/utils.py
scholarqa/config/__init__.py
scholarqa/config/config_setup.py
scholarqa/llms/__init__.py
scholarqa/llms/constants.py
scholarqa/llms/litellm_helper.py
scholarqa/llms/prompts.py
scholarqa/postprocess/__init__.py
scholarqa/postprocess/json_output_utils.py
scholarqa/preprocess/__init__.py
scholarqa/preprocess/query_preprocessor.py
scholarqa/rag/__init__.py
scholarqa/rag/multi_step_qa_pipeline.py
scholarqa/rag/retrieval.py
scholarqa/rag/retriever_base.py
scholarqa/rag/reranker/__init__.py
scholarqa/rag/reranker/modal_engine.py
scholarqa/rag/reranker/reranker_base.py
scholarqa/rag/reranker/modal_deploy/__init__.py
scholarqa/rag/reranker/modal_deploy/ai2-scholar-qa-reranker.py
scholarqa/rag/reranker/modal_deploy/custom_cross_encoder.py
scholarqa/rag/reranker/modal_deploy/reranker/__init__.py
scholarqa/rag/reranker/modal_deploy/reranker/custom_cross_encoder.py
scholarqa/state_mgmt/__init__.py
scholarqa/state_mgmt/local_state_mgr.py
scholarqa/state_mgmt/locked_state.py
scholarqa/table_generation/column_suggestion.py
scholarqa/table_generation/prompts.py
scholarqa/table_generation/table_generator.py
scholarqa/table_generation/table_model.py
scholarqa/table_generation/value_generation.py
scholarqa/trace/__init__.py
scholarqa/trace/event_traces.py
scholarqa/trace/trace_writer.py
ai2_scholar_qa-0.8.5.dist-info/METADATA
ai2_scholar_qa-0.8.5.dist-info/WHEEL
ai2_scholar_qa-0.8.5.dist-info/top_level.txt
ai2_scholar_qa-0.8.5.dist-info/RECORD
