Metadata-Version: 2.4
Name: ai2-scholar-qa
Version: 0.8.5
Summary: Python package to embed the Ai2 Scholar QA functionality in another application
Author-email: Amanpreet Singh <amanpreets@allenai.org>, Sergey Feldman <sergey@allenai.org>, Joseph Chang <josephc@allenai.org>
License: Apache-2.0
Project-URL: Homepage, https://scholarqa.allen.ai/
Project-URL: Documentation, https://github.com/allenai/ai2-scholarqa-lib
Project-URL: Repository, https://github.com/allenai/ai2-scholarqa-lib
Requires-Dist: fastapi==0.115.8
Requires-Dist: gunicorn==21.2.0
Requires-Dist: httpx
Requires-Dist: pydantic==2.*
Requires-Dist: python-json-logger==2.0.4
Requires-Dist: uvicorn[standard]
Requires-Dist: nora_lib==1.0.0
Requires-Dist: modal==1.0.2
Requires-Dist: pandas
Requires-Dist: jsonlines
Requires-Dist: googlesearch-python
Requires-Dist: backoff
Requires-Dist: numpy
Requires-Dist: pandas
Requires-Dist: requests
Requires-Dist: openai==1.106.1
Requires-Dist: bs4
Requires-Dist: fuzzy-match
Requires-Dist: googlesearch-python
Requires-Dist: tqdm
Requires-Dist: google-cloud-storage==2.18.2
Requires-Dist: filelock==3.16.1
Requires-Dist: litellm==1.76.2
Requires-Dist: pandas==2.2.2
Requires-Dist: diskcache==5.6.3
Requires-Dist: langsmith==0.1.142
Requires-Dist: anyascii==0.3.2
Requires-Dist: tenacity==9.1.2
Provides-Extra: dev
Requires-Dist: black; extra == "dev"
Requires-Dist: mypy; extra == "dev"
Requires-Dist: wheel; extra == "dev"
Requires-Dist: pytest; extra == "dev"
Provides-Extra: all
Requires-Dist: torch==2.3.1; extra == "all"
Requires-Dist: transformers==4.44.1; extra == "all"
Requires-Dist: sentencepiece; extra == "all"
Requires-Dist: hf-transfer==0.1.6; extra == "all"
Requires-Dist: huggingface_hub==0.23.4; extra == "all"
Requires-Dist: sentence-transformers==3.0.1; extra == "all"
Requires-Dist: peft; extra == "all"
Requires-Dist: black; extra == "all"
Requires-Dist: mypy; extra == "all"
Requires-Dist: wheel; extra == "all"
